packagenil/__init__.py
packagenil-0.1.dist-info/LICENSE.txt
packagenil-0.1.dist-info/METADATA
packagenil-0.1.dist-info/WHEEL
packagenil-0.1.dist-info/top_level.txt
packagenil-0.1.dist-info/RECORD
