Metadata-Version: 2.1
Name: packagenil
Version: 0.1
Summary: sampple code
Author: nilesh
License-File: LICENSE.txt
